media_parser/__init__.py
media_parser/context.py
media_parser/database/__init__.py
media_parser/database/base.py
media_parser/database/models.py
media_parser/models/__init__.py
media_parser/models/medias.py
media_parser/parsers/__init__.py
media_parser/parsers/base.py
media_parser/parsers/instagram.py
media_parser/parsers/reddit.py
media_parser/parsers/tiktok.py
media_parser/parsers/twitter.py
media_parser/parsers/youtube.py
media_parser/utils.py
media_parser-2.1.1.dist-info/LICENSE
media_parser-2.1.1.dist-info/METADATA
media_parser-2.1.1.dist-info/WHEEL
media_parser-2.1.1.dist-info/RECORD
